last_fm_api_client/__init__.py
last_fm_api_client/client.py
last_fm_api_client/models.py
last_fm_api_client-0.2.5.dist-info/METADATA
last_fm_api_client-0.2.5.dist-info/WHEEL
last_fm_api_client-0.2.5.dist-info/RECORD
