Metadata-Version: 2.1
Name: last-fm-api-client
Version: 0.2.5
Summary: 
Author: William04A
Author-email: 35110380+William04A@users.noreply.github.com
Requires-Python: >=3.9,<4.0
Classifier: Programming Language :: Python :: 3
Classifier: Programming Language :: Python :: 3.9
Classifier: Programming Language :: Python :: 3.10
Classifier: Programming Language :: Python :: 3.11
Requires-Dist: pydantic (>=1.10.8,<2.0.0)
